[{"date":"2021-05-12T04:00:00.000Z","open":11.84,"high":11.965,"low":11.73,"close":11.88,"adjClose":11.88,"volume":1244501,"symbol":"LLC.AX"},{"date":"2021-05-11T04:00:00.000Z","open":12.17,"high":12.28,"low":11.95,"close":12.03,"adjClose":12.03,"volume":1258437,"symbol":"LLC.AX"},{"date":"2021-05-10T04:00:00.000Z","open":12.06,"high":12.14,"low":11.99,"close":12.14,"adjClose":12.14,"volume":1563601,"symbol":"LLC.AX"},{"date":"2021-05-07T04:00:00.000Z","open":12.11,"high":12.24,"low":11.97,"close":12.05,"adjClose":12.05,"volume":1767838,"symbol":"LLC.AX"},{"date":"2021-05-06T04:00:00.000Z","open":12.21,"high":12.26,"low":11.95,"close":12.08,"adjClose":12.08,"volume":2069030,"symbol":"LLC.AX"},{"date":"2021-05-05T04:00:00.000Z","open":12.52,"high":12.59,"low":12.27,"close":12.34,"adjClose":12.34,"volume":2495477,"symbol":"LLC.AX"}]