[{"date":"2021-05-12T04:00:00.000Z","open":4.61,"high":4.64,"low":4.48,"close":4.5,"adjClose":4.5,"volume":16577970,"symbol":"QAN.AX"},{"date":"2021-05-11T04:00:00.000Z","open":4.7,"high":4.74,"low":4.61,"close":4.66,"adjClose":4.66,"volume":7906650,"symbol":"QAN.AX"},{"date":"2021-05-10T04:00:00.000Z","open":4.78,"high":4.83,"low":4.68,"close":4.71,"adjClose":4.71,"volume":5347615,"symbol":"QAN.AX"},{"date":"2021-05-07T04:00:00.000Z","open":4.72,"high":4.82,"low":4.69,"close":4.77,"adjClose":4.77,"volume":15359561,"symbol":"QAN.AX"},{"date":"2021-05-06T04:00:00.000Z","open":4.81,"high":4.83,"low":4.66,"close":4.74,"adjClose":4.74,"volume":8960115,"symbol":"QAN.AX"},{"date":"2021-05-05T04:00:00.000Z","open":4.88,"high":4.89,"low":4.81,"close":4.81,"adjClose":4.81,"volume":8388294,"symbol":"QAN.AX"}]